lavague/qa/__init__.py
lavague/qa/cli.py
lavague/qa/generator.py
lavague/qa/prompts.py
lavague/qa/utils.py
lavague_qa-0.0.6.dist-info/METADATA
lavague_qa-0.0.6.dist-info/WHEEL
lavague_qa-0.0.6.dist-info/entry_points.txt
lavague_qa-0.0.6.dist-info/RECORD
