Metadata-Version: 2.1
Name: lavague-qa
Version: 0.0.6
Summary: QA Automation with LaVague
Home-page: https://lavague.ai
License: Apache-2.0
Keywords: QA,testing,automation,cypress,agents,RAG,selenium,ai
Author: lavague-ai
Requires-Python: >=3.10.0,<4.0.0
Classifier: Development Status :: 3 - Alpha
Classifier: Intended Audience :: Developers
Classifier: License :: OSI Approved :: Apache Software License
Classifier: Programming Language :: Python :: 3
Classifier: Programming Language :: Python :: 3.10
Classifier: Programming Language :: Python :: 3.11
Classifier: Programming Language :: Python :: 3.12
Classifier: Topic :: Scientific/Engineering :: Artificial Intelligence
Classifier: Topic :: Software Development :: Libraries :: Application Frameworks
Classifier: Topic :: Software Development :: Libraries :: Python Modules
Requires-Dist: click (>=8.1.7,<9.0.0)
Requires-Dist: gherkin-official (>=28.0.0,<29.0.0)
Requires-Dist: lavague-core (>=0.2.33,<0.3.0)
Requires-Dist: lavague-drivers-selenium (>=0.2.6,<0.3.0)
Requires-Dist: lavague-tests (>=0.0.4,<0.0.5)
Requires-Dist: yaspin (>=3.0.2,<4.0.0)
Project-URL: Documentation, https://docs.lavague.ai/en/latest/
Project-URL: Repository, https://github.com/lavague-ai/LaVague/
